loopgpt/__init__.py
loopgpt/agent.py
loopgpt/aifunc.py
loopgpt/constants.py
loopgpt/logger.py
loopgpt/summarizer.py
loopgpt/embeddings/__init__.py
loopgpt/embeddings/azure_openai.py
loopgpt/embeddings/base.py
loopgpt/embeddings/hf.py
loopgpt/embeddings/openai_.py
loopgpt/loops/__init__.py
loopgpt/loops/cli.py
loopgpt/loops/repl.py
loopgpt/loops/ui.py
loopgpt/memory/__init__.py
loopgpt/memory/base_memory.py
loopgpt/memory/local_memory.py
loopgpt/models/__init__.py
loopgpt/models/azure_openai.py
loopgpt/models/base.py
loopgpt/models/hf.py
loopgpt/models/llama_.py
loopgpt/models/llama_cpp.py
loopgpt/models/openai_.py
loopgpt/models/stable_lm.py
loopgpt/tools/__init__.py
loopgpt/tools/agent_manager.py
loopgpt/tools/base_tool.py
loopgpt/tools/browser.py
loopgpt/tools/code.py
loopgpt/tools/filesystem.py
loopgpt/tools/google_search.py
loopgpt/tools/math.py
loopgpt/tools/memory_manager.py
loopgpt/tools/pdf.py
loopgpt/tools/shell.py
loopgpt/tools/simple_browser.py
loopgpt/tools/user_manager.py
loopgpt/utils/__init__.py
loopgpt/utils/openai_key.py
loopgpt/utils/spinner.py
loopgpt/utils/text.py
loopgpt-0.1.1.dist-info/LICENSE
loopgpt-0.1.1.dist-info/METADATA
loopgpt-0.1.1.dist-info/WHEEL
loopgpt-0.1.1.dist-info/entry_points.txt
loopgpt-0.1.1.dist-info/top_level.txt
loopgpt-0.1.1.dist-info/RECORD
