Metadata-Version: 2.1
Name: loopgpt
Version: 0.1.1
Summary: Modular Auto-GPT Framework
License-File: LICENSE
Requires-Dist: openai
Requires-Dist: bs4
Requires-Dist: selenium
Requires-Dist: numpy
Requires-Dist: tiktoken >=0.3.3
Requires-Dist: requests
Requires-Dist: colorama
Requires-Dist: duckduckgo-search >=2.9.4
Requires-Dist: google-api-python-client
Requires-Dist: webdriver-manager
Requires-Dist: simpleeval
Requires-Dist: python-dotenv
Requires-Dist: pypdf
Requires-Dist: bitsandbytes[hf] ; sys_platform != "win32"
Requires-Dist: bitsandbytes-windows[hf] ; sys_platform == "win32"
Provides-Extra: hf
Requires-Dist: transformers ; extra == 'hf'
Requires-Dist: sentence-transformers ; extra == 'hf'
Requires-Dist: accelerate ; extra == 'hf'
Requires-Dist: torch ; extra == 'hf'
